dot2tex/__init__.py
dot2tex/dot2tex.py
dot2tex/dotparsing.py
dot2tex-2.11.3.data/scripts/dot2tex
dot2tex-2.11.3.dist-info/AUTHORS
dot2tex-2.11.3.dist-info/LICENSE
dot2tex-2.11.3.dist-info/METADATA
dot2tex-2.11.3.dist-info/WHEEL
dot2tex-2.11.3.dist-info/entry_points.txt
dot2tex-2.11.3.dist-info/top_level.txt
dot2tex-2.11.3.dist-info/RECORD
